tidypandas/__init__.py
tidypandas/_unexported_utils.py
tidypandas/format.py
tidypandas/series_utils.py
tidypandas/tidy_accessor.py
tidypandas/tidy_utils.py
tidypandas/tidyframe_class.py
tidypandas/tidyselect.py
tidypandas-0.3.0.dist-info/LICENSE
tidypandas-0.3.0.dist-info/WHEEL
tidypandas-0.3.0.dist-info/METADATA
tidypandas-0.3.0.dist-info/RECORD
