Metadata-Version: 2.1
Name: tidypandas
Version: 0.3.0
Summary: A grammar of data manipulation for pandas inspired by tidyverse
Home-page: https://talegari.github.io/tidypandas/
License: MIT
Author: Srikanth Komala Sheshachala
Author-email: sri.teach@gmail.com
Maintainer: Srikanth Komala Sheshachala
Maintainer-email: sri.teach@gmail.com
Requires-Python: >=3.8,<4.0
Classifier: Development Status :: 4 - Beta
Classifier: License :: OSI Approved :: MIT License
Classifier: Programming Language :: Python :: 3
Classifier: Programming Language :: Python :: 3.10
Classifier: Programming Language :: Python :: 3.8
Classifier: Programming Language :: Python :: 3.9
Provides-Extra: skimpy
Requires-Dist: collections-extended (>=2.0.2)
Requires-Dist: pandas (>=1.0.0)
Requires-Dist: skimpy (>=0.0.5); extra == "skimpy"
Project-URL: Documentation, https://talegari.github.io/tidypandas/_build/html/autoapi/index.html
Project-URL: Repository, https://github.com/talegari/tidypandas
